fogml/__init__.py
fogml/anomaly/__init__.py
fogml/anomaly/detectors.py
fogml/generators/__init__.py
fogml/generators/anomaly_detector_generator.py
fogml/generators/arduino_generator.py
fogml/generators/base_generator.py
fogml/generators/bayes_code_generator.py
fogml/generators/generator.py
fogml/generators/mlp_code_generator.py
fogml/generators/qlearning_code_generator.py
fogml/generators/qstatesintervals_code_generator.py
fogml/generators/random_forest_generator.py
fogml/generators/scaler_generator.py
fogml/generators/tree_code_generator.py
fogml/generators/utils.py
fogml/generators/skeletons/__init__.py
fogml/generators/skeletons/bayes_skeleton.txt
fogml/generators/skeletons/kmeans_anomaly_skeleton.txt
fogml/generators/skeletons/min_max_scaler_skeleton.txt
fogml/generators/skeletons/qlearning_model_skeleton.txt
fogml/generators/skeletons/qstates_discretizer_skeleton.txt
fogml/generators/skeletons/random_forest_template.c
fogml/rl/__init__.py
fogml/rl/qlearning.py
fogml-0.0.8.dist-info/LICENSE
fogml-0.0.8.dist-info/METADATA
fogml-0.0.8.dist-info/WHEEL
fogml-0.0.8.dist-info/top_level.txt
fogml-0.0.8.dist-info/RECORD
