Metadata-Version: 2.1
Name: fogml
Version: 0.0.8
Summary: Tiny Federated ML for Fog Computing
Home-page: https://github.com/tszydlo/FogML
Author: Tomasz Szydlo
Author-email: tszydlo@agh.edu.pl
License: Apache 2.0
Project-URL: Bug Tracker, https://github.com/tszydlo/FogML/issues
Classifier: Programming Language :: Python :: 3
Classifier: License :: OSI Approved :: Apache Software License
Classifier: Operating System :: OS Independent
Requires-Python: >=3.6
License-File: LICENSE
